README.txt
bootstrap.py
buildout.cfg
setup.py
collective/__init__.py
collective.googleloader.egg-info/PKG-INFO
collective.googleloader.egg-info/SOURCES.txt
collective.googleloader.egg-info/dependency_links.txt
collective.googleloader.egg-info/entry_points.txt
collective.googleloader.egg-info/namespace_packages.txt
collective.googleloader.egg-info/not-zip-safe
collective.googleloader.egg-info/requires.txt
collective.googleloader.egg-info/top_level.txt
collective/googleloader/__init__.py
collective/googleloader/configure.zcml
collective/googleloader/interfaces.py
collective/googleloader/scripts.py
collective/googleloader/testing.py
collective/googleloader/profiles/default/metadata.xml
collective/googleloader/profiles/default/registry.xml
collective/googleloader/tests/__init__.py
collective/googleloader/tests/test_setup.py
docs/HISTORY.txt
docs/INSTALL.txt
docs/LICENSE.GPL
docs/LICENSE.txt