Metadata-Version: 1.0
Name: collective.googleloader
Version: 1.0b1
Summary: Integrate google loader (jsapi) into Plone
Home-page: http://svn.plone.org/svn/collective/collective.googleloader
Author: JeanMichel FRANCOIS aka toutpt
Author-email: toutpt@gmail.com
License: GPL
Platform: UNKNOWN
Classifier: Framework :: Plone
Classifier: Programming Language :: Python
